gr/__init__.py
gr/_version.py
gr/figplugin.dll
gr/htmplugin.dll
gr/libGKS.dll
gr/libGR.dll
gr/pgfplugin.dll
gr/svgplugin.dll
gr/wmfplugin.dll
gr/fonts/CenturySchL-Bold.afm
gr/fonts/CenturySchL-Bold.pfb
gr/fonts/CenturySchL-BoldItal.afm
gr/fonts/CenturySchL-BoldItal.pfb
gr/fonts/CenturySchL-Ital.afm
gr/fonts/CenturySchL-Ital.pfb
gr/fonts/CenturySchL-Roma.afm
gr/fonts/CenturySchL-Roma.pfb
gr/fonts/Dingbats.afm
gr/fonts/Dingbats.pfb
gr/fonts/NimbusMonL-Bold.afm
gr/fonts/NimbusMonL-Bold.pfb
gr/fonts/NimbusMonL-BoldObli.afm
gr/fonts/NimbusMonL-BoldObli.pfb
gr/fonts/NimbusMonL-Regu.afm
gr/fonts/NimbusMonL-Regu.pfb
gr/fonts/NimbusMonL-ReguObli.afm
gr/fonts/NimbusMonL-ReguObli.pfb
gr/fonts/NimbusRomNo9L-Medi.afm
gr/fonts/NimbusRomNo9L-Medi.pfb
gr/fonts/NimbusRomNo9L-MediItal.afm
gr/fonts/NimbusRomNo9L-MediItal.pfb
gr/fonts/NimbusRomNo9L-Regu.afm
gr/fonts/NimbusRomNo9L-Regu.pfb
gr/fonts/NimbusRomNo9L-ReguItal.afm
gr/fonts/NimbusRomNo9L-ReguItal.pfb
gr/fonts/NimbusSanL-Bold.afm
gr/fonts/NimbusSanL-Bold.pfb
gr/fonts/NimbusSanL-BoldCond.afm
gr/fonts/NimbusSanL-BoldCond.pfb
gr/fonts/NimbusSanL-BoldCondItal.afm
gr/fonts/NimbusSanL-BoldCondItal.pfb
gr/fonts/NimbusSanL-BoldItal.afm
gr/fonts/NimbusSanL-BoldItal.pfb
gr/fonts/NimbusSanL-Regu.afm
gr/fonts/NimbusSanL-Regu.pfb
gr/fonts/NimbusSanL-ReguCond.afm
gr/fonts/NimbusSanL-ReguCond.pfb
gr/fonts/NimbusSanL-ReguCondItal.afm
gr/fonts/NimbusSanL-ReguCondItal.pfb
gr/fonts/NimbusSanL-ReguItal.afm
gr/fonts/NimbusSanL-ReguItal.pfb
gr/fonts/StandardSymL.afm
gr/fonts/StandardSymL.pfb
gr/fonts/URWBookmanL-DemiBold.afm
gr/fonts/URWBookmanL-DemiBold.pfb
gr/fonts/URWBookmanL-DemiBoldItal.afm
gr/fonts/URWBookmanL-DemiBoldItal.pfb
gr/fonts/URWBookmanL-Ligh.afm
gr/fonts/URWBookmanL-Ligh.pfb
gr/fonts/URWBookmanL-LighItal.afm
gr/fonts/URWBookmanL-LighItal.pfb
gr/fonts/URWChanceryL-MediItal.afm
gr/fonts/URWChanceryL-MediItal.pfb
gr/fonts/URWGothicL-Book.afm
gr/fonts/URWGothicL-Book.pfb
gr-0.23.0.dist-info/DESCRIPTION.rst
gr-0.23.0.dist-info/METADATA
gr-0.23.0.dist-info/RECORD
gr-0.23.0.dist-info/WHEEL
gr-0.23.0.dist-info/metadata.json
gr-0.23.0.dist-info/top_level.txt
