Metadata-Version: 2.0
Name: gr
Version: 0.23.0
Summary: Python visualization framework
Home-page: http://gr-framework.org
Author: Josef Heinen
Author-email: j.heinen@fz-juelich.de
License: MIT License
Platform: Linux
Platform: OS X
Platform: Windows
Classifier: Framework :: IPython
Classifier: Intended Audience :: Science/Research
Classifier: License :: OSI Approved :: MIT License
Classifier: Operating System :: MacOS :: MacOS X
Classifier: Operating System :: Microsoft :: Windows
Classifier: Operating System :: POSIX :: Linux
Classifier: Programming Language :: Python
Classifier: Programming Language :: Python :: 2
Classifier: Programming Language :: Python :: 3
Classifier: Topic :: Multimedia :: Graphics
Classifier: Topic :: Scientific/Engineering :: Visualization
Requires: numpy
